mhd_model/__init__.py
mhd_model/domain_utils.py
mhd_model/log_utils.py
mhd_model/mhd_client.py
mhd_model/schema_utils.py
mhd_model/utils.py
mhd_model/commands/__init__.py
mhd_model/commands/cli.py
mhd_model/commands/create/__init__.py
mhd_model/commands/create/announcement.py
mhd_model/commands/create/create.py
mhd_model/commands/create/neo4j_input.py
mhd_model/commands/create/sdrf.py
mhd_model/commands/validate/__init__.py
mhd_model/commands/validate/announcement.py
mhd_model/commands/validate/mhd_file.py
mhd_model/commands/validate/validate.py
mhd_model/convertors/__init__.py
mhd_model/convertors/announcement/__init__.py
mhd_model/convertors/announcement/v0_1/__init__.py
mhd_model/convertors/announcement/v0_1/legacy/__init__.py
mhd_model/convertors/announcement/v0_1/legacy/mhd2announce.py
mhd_model/convertors/announcement/v0_1/ms/__init__.py
mhd_model/convertors/announcement/v0_1/ms/mhd2announce.py
mhd_model/convertors/mhd/__init__.py
mhd_model/convertors/mhd/convertor.py
mhd_model/convertors/neo4j_enabled_data/__init__.py
mhd_model/convertors/neo4j_enabled_data/v0_1/__init__.py
mhd_model/convertors/neo4j_enabled_data/v0_1/legacy/__init__.py
mhd_model/convertors/neo4j_enabled_data/v0_1/legacy/convertor.py
mhd_model/convertors/sdrf/__init__.py
mhd_model/convertors/sdrf/mhd2sdrf.py
mhd_model/model/__init__.py
mhd_model/model/definitions.py
mhd_model/model/v0_1/__init__.py
mhd_model/model/v0_1/announcement/__init__.py
mhd_model/model/v0_1/announcement/profiles/__init__.py
mhd_model/model/v0_1/announcement/profiles/base/__init__.py
mhd_model/model/v0_1/announcement/profiles/base/profile.py
mhd_model/model/v0_1/announcement/profiles/legacy/__init__.py
mhd_model/model/v0_1/announcement/profiles/legacy/profile.py
mhd_model/model/v0_1/announcement/profiles/ms/__init__.py
mhd_model/model/v0_1/announcement/profiles/ms/fields.py
mhd_model/model/v0_1/announcement/profiles/ms/profile.py
mhd_model/model/v0_1/announcement/validation/__init__.py
mhd_model-0.1.43.dist-info/licenses/LICENSE
mhd_model-0.1.43.dist-info/METADATA
mhd_model-0.1.43.dist-info/WHEEL
mhd_model-0.1.43.dist-info/entry_points.txt
mhd_model-0.1.43.dist-info/top_level.txt
mhd_model-0.1.43.dist-info/RECORD
