Metadata-Version: 2.4
Name: mhd-model
Version: 0.1.43
Summary: MetabolomicsHub Common Data Model
Author-email: MetabolomicsHub Team <help@metabolomicshub.org>
License-Expression: Apache-2.0
Requires-Python: >=3.10
License-File: LICENSE
Requires-Dist: bioregistry>=0.12.19
Requires-Dist: charset-normalizer>=3.4.2
Requires-Dist: dependency-injector>=4.48.1
Requires-Dist: email-validator>=2.2.0
Requires-Dist: httpx>=0.28.1
Requires-Dist: jsonpath-ng>=1.7.0
Requires-Dist: jsonschema>=4.24.0
Requires-Dist: pre-commit>=4.5.1
Requires-Dist: pydantic>=2.11.7
Requires-Dist: python-dateutil>=2.9.0.post0
Requires-Dist: pytz>=2025.2
Requires-Dist: pyyaml>=6.0.2
Requires-Dist: reachable>=0.7.0
Provides-Extra: neo4j
Requires-Dist: neo4j>=5.28.2; extra == "neo4j"
Dynamic: license-file
